polical/Get_Trello_MoodleEPN_Keys.py
polical/MateriaClass.py
polical/MateriasLoaderToDB.py
polical/PruebasUnitarias.py
polical/SendTaskToGCal.py
polical/SendTaskToTrello.py
polical/SimpleIcsToCSV.py
polical/TareaClass.py
polical/TareasCSVToBD.py
polical/__init__.py
polical/__main__.py
polical/configuration.py
polical/connectSQLite.py
polical/connection.py
polical/create_subject.py
polical/ejecutaScript.py
polical/get_GCal_Keys.py
polical/get_schedule.py
polical/icsReader.py
polical/polical.py
polical/polical_gui.py
polical/tasks.db
polical/tasks_processor.py
polical/test.py
polical/test2.py
polical/todo_generator.py
polical-1.1.3.dist-info/LICENSE.md
polical-1.1.3.dist-info/METADATA
polical-1.1.3.dist-info/WHEEL
polical-1.1.3.dist-info/top_level.txt
polical-1.1.3.dist-info/RECORD
