Metadata-Version: 2.1
Name: polical
Version: 1.1.3
Summary: Este es un programa hecho en python para sincronizar tareas existentes en el aula virtual de moodle EPN con una cuenta de Trello.
Home-page: https://github.com/andr3slelouch/PoliCal/
Author: Andrés Andrade
Author-email: andres.andrade17@outlook.com
License: BSD-3
Platform: UNKNOWN
Classifier: Programming Language :: Python :: 3
Classifier: License :: OSI Approved :: BSD License
Classifier: Operating System :: OS Independent
Classifier: Environment :: Console
Requires-Python: >=3.5
Requires-Dist: arrow
Requires-Dist: certifi
Requires-Dist: chardet
Requires-Dist: ics
Requires-Dist: idna
Requires-Dist: oauthlib
Requires-Dist: py-trello
Requires-Dist: python-dateutil
Requires-Dist: pytz
Requires-Dist: PyYAML
Requires-Dist: requests
Requires-Dist: requests-oauthlib
Requires-Dist: six
Requires-Dist: TatSu
Requires-Dist: urllib3
Requires-Dist: wget
Requires-Dist: mysql-connector-python
Requires-Dist: python-telegram-bot
